{
  "title": "Colors",
  "description": "Hex color codes that can be shared, cross-platform. They can be converted at point of usage, such as HSL for web or CMYK for print. The first two colors are used by the theme toggle script to set the theme color.",
  "items": [
    {
      "name": "Base Dark",
      "value": "#000000"
    },
    {
      "name": "Base Light",
      "value": "#ffffff"
    },
    {
      "name": "Primary Highlight",
      "value": "#fb923c"
    },
    {
      "name": "Secondary Highlight",
      "value": "#08bccb"
    },
    {
      "name": "Tertiary Highlight",
      "value": "#a977d5"
    }
  ]
}
